pbs_builder/__init__.py
pbs_builder/bin/pestat
pbs_builder/pestat.py
pbs_builder/pushover.py
pbs_builder/qbatch.py
pbs_builder/version.py
pbs_builder-0.4.9.dist-info/LICENSE
pbs_builder-0.4.9.dist-info/METADATA
pbs_builder-0.4.9.dist-info/WHEEL
pbs_builder-0.4.9.dist-info/entry_points.txt
pbs_builder-0.4.9.dist-info/RECORD
